{
  "resourceType": "ClinicalUseDefinition",
  "id": "DB08912-4746",
  "meta": {
    "profile": [
      "http://hl7.org/fhir/StructureDefinition/ClinicalUseDefinition"
    ],
    "lastUpdated": "2026-03-09T13:59:05.976552+00:00"
  },
  "type": "indication",
  "subject": [
    {
      "reference": "MedicationKnowledge/DB08912",
      "display": "Tafinlar"
    }
  ],
  "indication": {
    "diseaseSymptomProcedure": {
      "coding": [
        {
          "system": "http://purl.obolibrary.org/obo/mondo.owl",
          "code": "4746",
          "display": "myopathy of extraocular muscle"
        }
      ],
      "text": "myopathy of extraocular muscle"
    }
  },
  "extension": [
    {
      "url": "https://autxgnn.yao.care/fhir/StructureDefinition/prediction-source",
      "valueString": "TxGNN-KG"
    },
    {
      "url": "https://autxgnn.yao.care/fhir/StructureDefinition/research-only",
      "valueBoolean": true
    }
  ]
}